ipaymu/curl.py
ipaymu/ipaymu.py
ipaymu_python_api-0.0.1.dist-info/LICENSE
ipaymu_python_api-0.0.1.dist-info/METADATA
ipaymu_python_api-0.0.1.dist-info/WHEEL
ipaymu_python_api-0.0.1.dist-info/top_level.txt
ipaymu_python_api-0.0.1.dist-info/RECORD
