Metadata-Version: 2.1
Name: ipaymu-python-api
Version: 0.0.1
Summary: Payment Gateway iPaymu Python API
Author-email: iPaymu <support@ipaymu.com>
Project-URL: Homepage, https://github.com/ipaymu/ipaymu-python-api
Project-URL: Issues, https://github.com/ipaymu/ipaymu-python-api/issues
Classifier: Programming Language :: Python :: 3
Classifier: License :: OSI Approved :: MIT License
Classifier: Operating System :: OS Independent
Requires-Python: >=3.8
License-File: LICENSE
